{
  "extends": [
    "tslint-xo",
    "tslint-sonarts",
    "tslint-react"
  ],
  "rules": {
    "no-unnecessary-class": false,
    "no-implicit-dependencies": false,
    "no-non-null-assertion": false,
    "no-hardcoded-credentials": false,
    "no-identical-functions": false,
    "variable-name": [
      "allow-pascal-case"
    ],
    "file-name-casing": false,
    "quotemark": ["jsx-single", "jsx-double"],
    "jsx-no-multiline-js": false
  },
  "linterOptions": {
    "exclude": [
      "config/**/*.js",
      "node_modules/**/*.ts",
      "coverage/lcov-report/*.js"
    ]
  }
}
